ncmlyrics/__init__.py
ncmlyrics/__main__.py
ncmlyrics/__version__.py
ncmlyrics/api.py
ncmlyrics/app.py
ncmlyrics/constant.py
ncmlyrics/error.py
ncmlyrics/lrc.py
ncmlyrics/object.py
ncmlyrics/type.py
ncmlyrics/util.py
ncmlyrics-0.1.0a6.dist-info/METADATA
ncmlyrics-0.1.0a6.dist-info/WHEEL
ncmlyrics-0.1.0a6.dist-info/entry_points.txt
ncmlyrics-0.1.0a6.dist-info/licenses/LICENSE
ncmlyrics-0.1.0a6.dist-info/RECORD
