Metadata-Version: 2.3
Name: ncmlyrics
Version: 0.1.0a6
Dynamic: Description
Dynamic: Description-Content-Type
Summary: No description at now.
Project-URL: Homepage, https://github.com/Puqns67/ncmlyrics
Project-URL: Issues, https://github.com/Puqns67/ncmlyrics/issues
Author-email: Puqns67 <me@puqns67.icu>
License: GPL-3.0-or-later
Classifier: Development Status :: 1 - Planning
Classifier: Environment :: Console
Classifier: License :: OSI Approved :: GNU General Public License v3 or later (GPLv3+)
Classifier: Natural Language :: Chinese (Simplified)
Classifier: Operating System :: OS Independent
Classifier: Programming Language :: Python :: 3
Classifier: Programming Language :: Python :: 3 :: Only
Classifier: Programming Language :: Python :: 3.12
Classifier: Programming Language :: Python :: 3.13
Classifier: Programming Language :: Python :: Implementation :: CPython
Requires-Python: >=3.12
Requires-Dist: click>=8
Requires-Dist: httpx
Requires-Dist: platformdirs>=4
Requires-Dist: rich>=13
Provides-Extra: brotli
Requires-Dist: brotli; (platform_python_implementation == 'CPython') and extra == 'brotli'
Requires-Dist: brotlicffi; (platform_python_implementation != 'CPython') and extra == 'brotli'
Provides-Extra: http2
Requires-Dist: h2<5,>=3; extra == 'http2'
Provides-Extra: zstd
Requires-Dist: zstandard>=0.18.0; extra == 'zstd'
